{"data":{"transmitterListing20110702Json":{"antennaHeight":"15","antennaPattern":"OD","areaServed":"Flowerdale/Hazeldene","bSL":null,"band":"FM","callsign":"3ABCRR","easting":"347700","frequency":"97.3","hoursofOperation":null,"id":"f73312fc-9264-4e92-9682-59eb88ed9f44","latitude":-37.34361111,"licenceArea":null,"licenceAreaID":null,"licenceNumber":"1159647","longitude":145.28055556,"maximumCMF":null,"maximumERP":"100","northing":"5865600","onAirID":"ABC Local Radio","polarisation":"M","purpose":"Retransmission","siteId":"153196","siteName":"Broadcast Planning Site Hill 1km west of HAZELEDENE","state":"VIC","status":"Issued","technicalSpecificationNumber":"1130751","transmitterPower":null,"zone":"55"}},"pageContext":{"transmitterID":"f73312fc-9264-4e92-9682-59eb88ed9f44"}}