{"data":{"transmitterListing20110702Json":{"antennaHeight":"65","antennaPattern":"OD","areaServed":"Greenvale","bSL":null,"band":"FM","callsign":"4ABCRN","easting":"287600","frequency":"101.9","hoursofOperation":null,"id":"02c36b17-fd7b-4046-adcd-830237570cf7","latitude":-19.00305556,"licenceArea":null,"licenceAreaID":null,"licenceNumber":"1198701","longitude":144.98222222,"maximumCMF":null,"maximumERP":"50","northing":"7897600","onAirID":"ABC Radio National","polarisation":"M","purpose":"National","siteId":"41014","siteName":"Broadcast Site GREENVALE","state":"QLD","status":"Issued","technicalSpecificationNumber":"10003931","transmitterPower":null,"zone":"55"}},"pageContext":{"transmitterID":"02c36b17-fd7b-4046-adcd-830237570cf7"}}