{"data":{"transmitterListing20110702Json":{"antennaHeight":"20","antennaPattern":"OD","areaServed":"Warwick","bSL":"1150093","band":"FM","callsign":"4SDB","easting":"402385","frequency":"89.3","hoursofOperation":null,"id":"b46823fe-fd45-49c3-8acc-057395f77c8f","latitude":-28.22583333,"licenceArea":"WARWICK RA2","licenceAreaID":"701","licenceNumber":"1170414","longitude":152.005,"maximumCMF":null,"maximumERP":"2000","northing":"6877340","onAirID":"Rainbow FM","polarisation":"V","purpose":"Community","siteId":"152266","siteName":"Broadcast Site Warwick Shire Council Bldg Willi St WARWICK","state":"QLD","status":"Issued","technicalSpecificationNumber":"10008128","transmitterPower":null,"zone":"56"}},"pageContext":{"transmitterID":"b46823fe-fd45-49c3-8acc-057395f77c8f"}}