{"data":{"transmitterListing20110702Json":{"antennaHeight":"52","antennaPattern":"OD","areaServed":"Barcaldine","bSL":null,"band":"FM","callsign":"4JJJ","easting":"325676","frequency":"105.7","hoursofOperation":null,"id":"a2875a12-a3ca-47ce-aaf2-1332c1173aa9","latitude":-23.55805556,"licenceArea":null,"licenceAreaID":null,"licenceNumber":"1900045","longitude":145.29194444,"maximumCMF":null,"maximumERP":"100","northing":"7393646","onAirID":"Triple J","polarisation":"V","purpose":"Retransmission","siteId":"18096","siteName":"Water Tower Pine & Yew Sts BARCALDINE","state":"QLD","status":"Issued","technicalSpecificationNumber":"1132871","transmitterPower":null,"zone":"55"}},"pageContext":{"transmitterID":"a2875a12-a3ca-47ce-aaf2-1332c1173aa9"}}