{"data":{"transmitterListing20110702Json":{"antennaHeight":"84","antennaPattern":"OD","areaServed":"Adelaide","bSL":"5272","band":"AM","callsign":"5RPH","easting":"277600","frequency":"1197","hoursofOperation":null,"id":"68006bbd-f678-4650-9752-eab440a0e882","latitude":-34.83805556,"licenceArea":"ADELAIDE RA1","licenceAreaID":"499","licenceNumber":"1170627","longitude":138.56777778,"maximumCMF":"455","maximumERP":null,"northing":"6142200","onAirID":"RPH Adelaide","polarisation":"V","purpose":"Community","siteId":"22338","siteName":"Broadcasting site South Terrace WINGFIELD","state":"SA","status":"Issued","technicalSpecificationNumber":"5272001","transmitterPower":"2000","zone":"54"}},"pageContext":{"transmitterID":"68006bbd-f678-4650-9752-eab440a0e882"}}