{"data":{"transmitterListing20110702Json":{"antennaHeight":"198","antennaPattern":"OD","areaServed":"Brisbane","bSL":null,"band":"AM","callsign":"4QR","easting":"501620","frequency":"612","hoursofOperation":null,"id":"0ca707c5-5e90-4f74-a7b3-eb5c0dffd873","latitude":-27.31305556,"licenceArea":null,"licenceAreaID":null,"licenceNumber":"1198655","longitude":153.01638889,"maximumCMF":"2790","maximumERP":null,"northing":"6978870","onAirID":"ABC Brisbane","polarisation":"V","purpose":"National","siteId":"12661","siteName":"4QR Site BALD HILLS","state":"QLD","status":"Issued","technicalSpecificationNumber":"4031001","transmitterPower":"50000","zone":"56"}},"pageContext":{"transmitterID":"0ca707c5-5e90-4f74-a7b3-eb5c0dffd873"}}