{"data":{"transmitterListing20110702Json":{"antennaHeight":"30","antennaPattern":"OD","areaServed":"Dubbo (City)","bSL":"10054","band":"FM","callsign":"2ZOO","easting":"651100","frequency":"91.1","hoursofOperation":null,"id":"2a3db4ec-c7db-4a0c-bbd5-488942ac1238","latitude":-32.2475,"licenceArea":"DUBBO RA1","licenceAreaID":"366","licenceNumber":"1149509","longitude":148.60388889,"maximumCMF":null,"maximumERP":"100","northing":"6430960","onAirID":"SBS Radio","polarisation":"M","purpose":"Commercial","siteId":"130174","siteName":"Radio 2DU Studios 33 Carrington Av DUBBO","state":"NSW","status":"Issued","technicalSpecificationNumber":"1130143","transmitterPower":null,"zone":"55"}},"pageContext":{"transmitterID":"2a3db4ec-c7db-4a0c-bbd5-488942ac1238"}}