{"data":{"transmitterListing20110702Json":{"antennaHeight":"57","antennaPattern":"OD","areaServed":"Swan Hill","bSL":"10380","band":"AM","callsign":"3SH","easting":"734300","frequency":"1332","hoursofOperation":null,"id":"f8eadd88-7d77-4f8d-8f1e-0f84d75ce1c8","latitude":-35.41111111,"licenceArea":"SWAN HILL RA1","licenceAreaID":"438","licenceNumber":"1385027","longitude":143.58027778,"maximumCMF":"450","maximumERP":null,"northing":"6078300","onAirID":"3SH","polarisation":"V","purpose":"Commercial","siteId":"40555","siteName":"3SH Site Pental SWAN HILL","state":"VIC","status":"Issued","technicalSpecificationNumber":"10005797","transmitterPower":"2000","zone":"54"}},"pageContext":{"transmitterID":"f8eadd88-7d77-4f8d-8f1e-0f84d75ce1c8"}}