{"data":{"transmitterListing20110702Json":{"antennaHeight":"20","antennaPattern":"OD","areaServed":"Leigh Ck Coalfield","bSL":null,"band":"FM","callsign":"5ABCRR","easting":"253732","frequency":"99.3","hoursofOperation":null,"id":"94d3d8e3-a28c-41b5-8aaa-19c619d1ac47","latitude":-30.49555556,"licenceArea":null,"licenceAreaID":null,"licenceNumber":"1153818","longitude":138.43416667,"maximumCMF":null,"maximumERP":"200","northing":"6623485","onAirID":"ABC Local Radio","polarisation":"V","purpose":"Retransmission","siteId":"151333","siteName":"Broadcast Site M6 Viewing Platform LEIGH CREEK COALFIELD","state":"SA","status":"Issued","technicalSpecificationNumber":"7085001","transmitterPower":null,"zone":"54"}},"pageContext":{"transmitterID":"94d3d8e3-a28c-41b5-8aaa-19c619d1ac47"}}