{"data":{"transmitterListing20110702Json":{"antennaHeight":"120","antennaPattern":"DA","areaServed":"Melbourne","bSL":"1150695","band":"FM","callsign":"3TSC","easting":"354980","frequency":"89.9","hoursofOperation":null,"id":"682bab4c-3083-4e40-888c-7f43542e4802","latitude":-37.82972222,"licenceArea":"MELBOURNE RA1","licenceAreaID":"531","licenceNumber":"1170727","longitude":145.35194444,"maximumCMF":null,"maximumERP":"56000","northing":"5811755","onAirID":"Light FM","polarisation":"M","purpose":"Community","siteId":"12010","siteName":"GTV-9 Tower Observatory Road MT DANDENONG","state":"VIC","status":"Issued","technicalSpecificationNumber":"10008366","transmitterPower":null,"zone":"55"}},"pageContext":{"transmitterID":"682bab4c-3083-4e40-888c-7f43542e4802"}}