{"data":{"transmitterListing20110702Json":{"antennaHeight":"20","antennaPattern":"DA","areaServed":"Coonalpyn","bSL":"10147","band":"FM","callsign":"8SAT","easting":"377800","frequency":"97.7","hoursofOperation":null,"id":"061462f8-eea8-4ff7-a314-edf06770641e","latitude":-35.67527778,"licenceArea":"REMOTE COMMERCIAL RADIO SERVICE CENTRAL ZONE RA1","licenceAreaID":"496","licenceNumber":"1158868","longitude":139.64944444,"maximumCMF":null,"maximumERP":"3000","northing":"6051200","onAirID":"Flow FM","polarisation":"V","purpose":"Commercial","siteId":"153385","siteName":"Coorong Council Tower Binnie Lookout Coonalpyn Road MENINGIE","state":"SA","status":"Issued","technicalSpecificationNumber":"10012415","transmitterPower":null,"zone":"54"}},"pageContext":{"transmitterID":"061462f8-eea8-4ff7-a314-edf06770641e"}}