{"data":{"transmitterListing20110702Json":{"antennaHeight":"33","antennaPattern":"OD","areaServed":"Broken Hill","bSL":"10245","band":"FM","callsign":"2HIL","easting":"543000","frequency":"106.9","hoursofOperation":null,"id":"aff8fdb0-0e22-494d-aa23-e3fb1031fba1","latitude":-31.96361111,"licenceArea":"BROKEN HILL RA1","licenceAreaID":"502","licenceNumber":"1384922","longitude":141.455,"maximumCMF":null,"maximumERP":"160","northing":"6463500","onAirID":"Hill FM","polarisation":"V","purpose":"Commercial","siteId":"11419","siteName":"2BH Studio Building BROKEN HILL","state":"NSW","status":"Issued","technicalSpecificationNumber":"10004140","transmitterPower":null,"zone":"54"}},"pageContext":{"transmitterID":"aff8fdb0-0e22-494d-aa23-e3fb1031fba1"}}