{"data":{"transmitterListing20110702Json":{"antennaHeight":"80","antennaPattern":"OD","areaServed":"Jericho","bSL":null,"band":"FM","callsign":"4ABCRN","easting":"424012","frequency":"107.7","hoursofOperation":null,"id":"1886a840-2f51-4015-92d5-33a853c341cc","latitude":-23.62638889,"licenceArea":null,"licenceAreaID":null,"licenceNumber":"1198771","longitude":146.255,"maximumCMF":null,"maximumERP":"320","northing":"7386924","onAirID":"ABC Radio National","polarisation":"M","purpose":"National","siteId":"15272","siteName":"Broadcast/Telstra Site 13 km E of JERICHO","state":"QLD","status":"Issued","technicalSpecificationNumber":"10003870","transmitterPower":null,"zone":"55"}},"pageContext":{"transmitterID":"1886a840-2f51-4015-92d5-33a853c341cc"}}