{"data":{"transmitterListing20110702Json":{"antennaHeight":"20","antennaPattern":"OD","areaServed":"Texas","bSL":null,"band":"FM","callsign":"4RBL","easting":"321258","frequency":"94.5","hoursofOperation":null,"id":"bcb5847b-6956-44e9-b238-6d76bd967ad9","latitude":-28.85888889,"licenceArea":null,"licenceAreaID":null,"licenceNumber":"1147323","longitude":151.1675,"maximumCMF":null,"maximumERP":"50","northing":"6806253","onAirID":"Rebel FM","polarisation":"M","purpose":"Commercial","siteId":"200610","siteName":"SES FWS Site TEXAS","state":"QLD","status":"Issued","technicalSpecificationNumber":"10013180","transmitterPower":null,"zone":"56"}},"pageContext":{"transmitterID":"bcb5847b-6956-44e9-b238-6d76bd967ad9"}}