{"data":{"transmitterListing20110702Json":{"antennaHeight":"30","antennaPattern":"OD","areaServed":"Ingham","bSL":null,"band":"FM","callsign":null,"easting":"417086","frequency":"96.9","hoursofOperation":null,"id":"ae2be755-7e13-4a68-8f16-cbc2e0c07c1b","latitude":-18.69111111,"licenceArea":null,"licenceAreaID":null,"licenceNumber":"1154749","longitude":146.21361111,"maximumCMF":null,"maximumERP":"300","northing":"7933153","onAirID":null,"polarisation":"V","purpose":"HPON","siteId":"151730","siteName":"Broadcast Site MT MERCER","state":"QLD","status":"Issued","technicalSpecificationNumber":"10007655","transmitterPower":null,"zone":"55"}},"pageContext":{"transmitterID":"ae2be755-7e13-4a68-8f16-cbc2e0c07c1b"}}