{"data":{"transmitterListing20110702Json":{"antennaHeight":"25","antennaPattern":"DA","areaServed":"Bairnsdale","bSL":"1150756","band":"FM","callsign":"3TFM","easting":"549310","frequency":"99.9","hoursofOperation":null,"id":"dbf871f9-6963-444f-b624-eab861364d8a","latitude":-37.70777778,"licenceArea":"SALE RA1","licenceAreaID":"439","licenceNumber":"1170644","longitude":147.55916667,"maximumCMF":null,"maximumERP":"5000","northing":"5826440","onAirID":"TRFM","polarisation":"M","purpose":"Commercial","siteId":"12064","siteName":"Riviera Communications Tower 14 km NNW of Bairnsdale MT TAYLOR","state":"VIC","status":"Issued","technicalSpecificationNumber":"10011107","transmitterPower":null,"zone":"55"}},"pageContext":{"transmitterID":"dbf871f9-6963-444f-b624-eab861364d8a"}}