{"data":{"transmitterListing20110702Json":{"antennaHeight":"30","antennaPattern":"OD","areaServed":"Hervey Bay","bSL":"1150062","band":"FM","callsign":"4FCR","easting":"483300","frequency":"107.5","hoursofOperation":null,"id":"cf64463f-f9dd-47b6-901b-39c10f3042b8","latitude":-25.31194444,"licenceArea":"HERVEY BAY RA1","licenceAreaID":"683","licenceNumber":"1171594","longitude":152.83388889,"maximumCMF":null,"maximumERP":"500","northing":"7200460","onAirID":"Fraser Coast Community Radio","polarisation":"M","purpose":"Community","siteId":"16641","siteName":"Community Radio Site GHOST HILL","state":"QLD","status":"Issued","technicalSpecificationNumber":"10007996","transmitterPower":null,"zone":"56"}},"pageContext":{"transmitterID":"cf64463f-f9dd-47b6-901b-39c10f3042b8"}}