{"data":{"transmitterListing20110702Json":{"antennaHeight":"100","antennaPattern":"OD","areaServed":"Hobart","bSL":"4217","band":"FM","callsign":"7XXX","easting":"519185","frequency":"107.3","hoursofOperation":null,"id":"40f6086a-b95b-45e3-8391-9c89f91683c4","latitude":-42.89916667,"licenceArea":"HOBART RA1","licenceAreaID":"520","licenceNumber":"1384884","longitude":147.235,"maximumCMF":null,"maximumERP":"36000","northing":"5250351","onAirID":"Heart 107.3","polarisation":"M","purpose":"Commercial","siteId":"32830","siteName":"NTA Tower MT WELLINGTON","state":"TAS","status":"Issued","technicalSpecificationNumber":"4217001","transmitterPower":null,"zone":"55"}},"pageContext":{"transmitterID":"40f6086a-b95b-45e3-8391-9c89f91683c4"}}