{"data":{"transmitterListing20110702Json":{"antennaHeight":"10","antennaPattern":"OD","areaServed":"Mt Keith (Mine Village)","bSL":null,"band":"FM","callsign":"6ABCRR","easting":"261000","frequency":"105.3","hoursofOperation":null,"id":"53a0147c-14a0-483e-8d00-eb396edcdc13","latitude":-27.23694444,"licenceArea":null,"licenceAreaID":null,"licenceNumber":"1565248","longitude":120.58638889,"maximumCMF":null,"maximumERP":"20","northing":"6985000","onAirID":"ABC Local Radio","polarisation":"V","purpose":"Retransmission","siteId":"29744","siteName":"Broadcast Site Mine Village Mt Keith 75km North of LEINSTER","state":"WA","status":"Issued","technicalSpecificationNumber":"1132630","transmitterPower":null,"zone":"51"}},"pageContext":{"transmitterID":"53a0147c-14a0-483e-8d00-eb396edcdc13"}}