{"data":{"transmitterListing20110702Json":{"antennaHeight":"30","antennaPattern":"OD","areaServed":"Stanthorpe","bSL":null,"band":"FM","callsign":"4BRZ","easting":"396991","frequency":"90.1","hoursofOperation":null,"id":"86d0e1d1-280e-4124-b3ea-c37a082d8ec8","latitude":-28.655,"licenceArea":null,"licenceAreaID":null,"licenceNumber":"1159656","longitude":151.94583333,"maximumCMF":null,"maximumERP":"100","northing":"6829751","onAirID":"Breeze FM","polarisation":"M","purpose":"Retransmission","siteId":"35078","siteName":"Broadcast Site Mt Marlay STANTHORPE","state":"QLD","status":"Issued","technicalSpecificationNumber":"10014741","transmitterPower":null,"zone":"56"}},"pageContext":{"transmitterID":"86d0e1d1-280e-4124-b3ea-c37a082d8ec8"}}