{"data":{"transmitterListing20110702Json":{"antennaHeight":"20","antennaPattern":"OD","areaServed":"Wongan Hills","bSL":null,"band":"FM","callsign":"6ABCRN","easting":"473571","frequency":"107.9","hoursofOperation":null,"id":"7a497ed5-bd75-4c4e-8e39-56f2f5f60aa2","latitude":-30.89138889,"licenceArea":null,"licenceAreaID":null,"licenceNumber":"1194414","longitude":116.72333333,"maximumCMF":null,"maximumERP":"30","northing":"6582362","onAirID":"ABC Radio National","polarisation":"V","purpose":"Retransmission","siteId":"153651","siteName":"Shire Site Lot 486 Quinlan Street WONGAN HILLS","state":"WA","status":"Issued","technicalSpecificationNumber":"10014881","transmitterPower":null,"zone":"50"}},"pageContext":{"transmitterID":"7a497ed5-bd75-4c4e-8e39-56f2f5f60aa2"}}