{"data":{"transmitterListing20110702Json":{"antennaHeight":"20","antennaPattern":"OD","areaServed":"Naracoorte","bSL":"10312","band":"FM","callsign":"5SEF","easting":"479357","frequency":"100.9","hoursofOperation":null,"id":"f5d7c1bc-cbbb-40cf-9856-94feec1383a8","latitude":-36.95222222,"licenceArea":"MT GAMBIER RA1","licenceAreaID":"474","licenceNumber":"1155311","longitude":140.76805556,"maximumCMF":null,"maximumERP":"100","northing":"5910387","onAirID":"Star FM","polarisation":"M","purpose":"Commercial","siteId":"23720","siteName":"Council & CFS site Smith Street East NARACOORTE","state":"SA","status":"Issued","technicalSpecificationNumber":"10010529","transmitterPower":null,"zone":"54"}},"pageContext":{"transmitterID":"f5d7c1bc-cbbb-40cf-9856-94feec1383a8"}}